gdbundle_voltron/__init__.py
gdbundle_voltron/gdb_loader.py
gdbundle_voltron/lldb_loader.py
gdbundle_voltron-0.1.7.post2.dist-info/WHEEL
gdbundle_voltron-0.1.7.post2.dist-info/METADATA
gdbundle_voltron-0.1.7.post2.dist-info/RECORD
